mlops_codex/__init__.py
mlops_codex/__model_states.py
mlops_codex/__utils.py
mlops_codex/base.py
mlops_codex/dataset.py
mlops_codex/datasources.py
mlops_codex/exceptions.py
mlops_codex/external_monitoring.py
mlops_codex/http_request_handler.py
mlops_codex/logger_config.py
mlops_codex/logging.py
mlops_codex/model.py
mlops_codex/preprocessing.py
mlops_codex/training.py
mlops_codex/validations.py
mlops_codex/shared/__init__.py
mlops_codex/shared/constants.py
mlops_codex/shared/data_transmitter.py
mlops_codex/shared/utils.py
datarisk_mlops_codex-4.0.2.dist-info/METADATA
datarisk_mlops_codex-4.0.2.dist-info/WHEEL
datarisk_mlops_codex-4.0.2.dist-info/entry_points.txt
datarisk_mlops_codex-4.0.2.dist-info/licenses/LICENSE.txt
datarisk_mlops_codex-4.0.2.dist-info/RECORD
