Metadata-Version: 2.4
Name: datarisk-mlops-codex
Version: 4.0.2
Summary: A Python SDK for interacting with the DataRisk MLOps API
License-Expression: MIT
License-File: LICENSE.txt
Requires-Python: >=3.10
Requires-Dist: cloudpickle>=3.1.1
Requires-Dist: lazy-imports>=1.0.1
Requires-Dist: loguru>=0.7.3
Requires-Dist: pandas>=2.3.3
Requires-Dist: plotly>=6.3.1
Requires-Dist: pydantic>=2.12.0
Requires-Dist: requests==2.32.5
Requires-Dist: seaborn>=0.13.2
